{
  "schema_version": "0.1",
  "venue_key": "alt",
  "year": 2024,
  "source": "pmlr",
  "baseline": "papercopilot",
  "generated_at": "2026-06-17T09:23:44Z",
  "status": "no_baseline",
  "min_count_ratio": 0.95,
  "counts": {
    "ours": 45,
    "baseline": 0,
    "title_overlap": 0,
    "count_ratio": 1.0,
    "overlap_ratio": 1.0
  },
  "known_baseline_issues": [],
  "samples": {
    "missing_from_ours": [],
    "extra_in_ours": [
      "a mechanism for sample efficient in context learning for sparse retrieval tasks",
      "a polynomial time pure differentially private estimator for binary product distributions",
      "adaptive combinatorial maximization beyond approximate greedy policies",
      "adversarial contextual bandits go kernelized",
      "adversarial online collaborative filtering",
      "agnostic membership query learning with nontrivial savings new results and techniques",
      "algorithmic learning theory 2024 preface",
      "alternating minimization for generalized rank one matrix sensing sharp predictions from a random initialization",
      "computation with sequences of assemblies in a model of the brain",
      "concentration of empirical barycenters in metric spaces",
      "corruption robust lipschitz contextual search",
      "crimed lower and upper bounds on regret for bandits with unbounded stochastic corruption",
      "differentially private non convex optimization under the kl condition with optimal rates",
      "distances for markov chains and their differentiation",
      "dueling optimization with a monotone adversary",
      "efficient agnostic learning with average smoothness",
      "importance weighted offline learning done right",
      "improving adaptive online learning using refined discretization",
      "learning bounded degree polytrees with known skeleton",
      "learning hypertrees from shortest path queries",
      "learning spanning forests optimally in weighted undirected graphs with cut queries",
      "mixtures of gaussians are privately learnable with a polynomial number of samples",
      "multiclass learnability does not imply sample compression",
      "multiclass online learnability under bandit feedback",
      "near continuous time reinforcement learning for continuous state action spaces",
      "not all learnable distribution classes are privately learnable",
      "on the computational benefit of multimodal learning",
      "on the sample complexity of two layer networks lipschitz vs element wise lipschitz activation",
      "online infinite dimensional regression learning linear operators",
      "online recommendations for agents with discounted adaptive preferences",
      "optimal regret bounds for collaborative learning in bandits",
      "partially interpretable models with guarantees on coverage and accuracy",
      "predictor rejector multi class abstention theoretical analysis and algorithms",
      "private pac learning may be harder than online learning",
      "provable accelerated convergence of nesterov s momentum for deep relu neural networks",
      "redex beyond fixed representation methods via convex optimization",
      "semi supervised group dro combating sparsity with unlabeled data",
      "slowly changing adversarial bandit algorithms are efficient for discounted mdps",
      "the attractor of the replicator dynamic in zero sum games",
      "the complexity of non stationary reinforcement learning",
      "the dimension of self directed learning",
      "the impossibility of parallelizing boosting",
      "tight bounds for local glivenko cantelli",
      "tight bounds for maximum ell 1 margin classifiers",
      "universal representation of permutation invariant functions on vectors and tensors"
    ]
  }
}
